setup.py
django_super_cache/__init__.py
django_super_cache/backends.py
django_super_cache/exceptions.py
django_super_cache/messages.py
django_super_cache/middleware.py
django_super_cache/settings.py
django_super_cache/utils.py
django_super_cache.egg-info/PKG-INFO
django_super_cache.egg-info/SOURCES.txt
django_super_cache.egg-info/dependency_links.txt
django_super_cache.egg-info/entry_points.txt
django_super_cache.egg-info/pbr.json
django_super_cache.egg-info/requires.txt
django_super_cache.egg-info/top_level.txt
django_super_cache.egg-info/zip-safe