Metadata-Version: 1.1
Name: django-super-cache
Version: 0.1a1
Summary: a page cache plugin, enable you to cache your single page to file or redis.
Home-page: https://github.com/youngershen/django-super-cache
Author: younger shen
Author-email: younger.x.shen@gmail.com
License: MIT
Keywords: django-super-cache,django,cache,page,page cache
Platform: UNKNOWN
Classifier: Development Status :: 2 - Pre-Alpha
Classifier: Environment :: Web Environment
Classifier: Framework :: Django
Classifier: Intended Audience :: Developers
Classifier: License :: OSI Approved :: MIT License
Classifier: Natural Language :: English
Classifier: Programming Language :: Python :: 2.7
